jax_mcp/__init__.py
jax_mcp/__main__.py
jax_mcp/docs_source.py
jax_mcp/server.py
jax_mcp/tools/__init__.py
jax_mcp/tools/get_documentation.py
jax_mcp/tools/jax_checker.py
jax_mcp/tools/list_sections.py
jax_mcp-0.1.0.dist-info/METADATA
jax_mcp-0.1.0.dist-info/WHEEL
jax_mcp-0.1.0.dist-info/entry_points.txt
jax_mcp-0.1.0.dist-info/RECORD
