Metadata-Version: 2.4
Name: jax-mcp
Version: 0.1.0
Summary: MCP server for JAX documentation
Requires-Python: >=3.10
Requires-Dist: httpx>=0.27.0
Requires-Dist: mcp>=1.0.0
Requires-Dist: pyyaml>=6.0
Provides-Extra: dev
Requires-Dist: pytest-asyncio>=0.23.0; extra == 'dev'
Requires-Dist: pytest>=7.0; extra == 'dev'
